{"B07JWB1X9Q": {"Positive": {"Ref": ["B1KDXoxqPfS._SL1600_.jpg", "91nujLLZ-QL._SL1600_.jpg", "81RhGxtqp4L._SL1600_.jpg", "71uATWBePmL._SL1600_.jpg"], "Eval": ["61-scf8ze6L.jpg", "71vS2kj7V2L._SL1600_.jpg", "81VO6VCUfdL._SL1600_.jpg", "B15oOJmVTIS._SL1600_.jpg", "C1p4IuTjmLS._SL1600_.jpg", "71vUTp+prmL.jpg", "71zZuaDbVAL.jpg", "71yyxgXirCL.jpg", "71-zrbGWDzL.jpg", "71B8+79wJOL._SL1600_.jpg", "716LVXzA64L._SL1600_.jpg", "815n9XP25mL._SL1600_.jpg", "719INZIAJrL.jpg", "71LgUrFlqTL._SL1600_.jpg", "719dKjqcXKL._SL1600_.jpg", "C1rjq+gYy5S._SL1600_.jpg", "619gQNS35AL.jpg", "81sVejyfoxL._SL1600_.jpg", "B1oqohfaGpS._SL1600_.jpg"]}, "Negative": ["616q3uafM3L._SL1600_.jpg", "71DR67E52mL.jpg", "61jutSV5ePL.jpg", "619OJ8nXurL._SL1600_.jpg", "71jcAMQr4FL.jpg", "712P6xdbupL._SL1600_.jpg", "71dWlk03ZQL.jpg", "71G+6mE74LL.jpg", "61-lxm6EtwL._SL1600_.jpg", "61cNmRS-IpL.jpg", "7199TmfeVlL._SL1600_.jpg", "710Q5lq1YpL.jpg", "71zEsKqH6oL.jpg", "41uvWtKFSXL._SL1600_.jpg", "618a20NEHeL._SL1600_.jpg", "61raKw9nHuL._SL1600_.jpg", "61Kwq8C9+6L.jpg", "71ORISnnwbL.jpg", "B1+ZTqPszAS._SL1600_.jpg", "71OgqllR7yL.jpg", "71B+nmT4YmL._SL1600_.jpg", "71pOylGP1ML.jpg", "71D0ptAO+aL.jpg", "61U8+fQOcuL._SL1600_.jpg", "71V8pGecqpL.jpg", "717Nr-Ku4yL._SL1600_.jpg", "C1z6w4RZgQS._SL1600_.jpg", "710fDlnvwML.jpg", "B07JWB1X9Q-1.jpg", "B07JWB1X9Q-2.jpg", "B07JWB1X9Q-3.jpg"]}, "B01H1LM9TK": {"Positive": {"Ref": ["71UujswjuBL._SL1600_.jpg", "716KdqjmXlL.jpg", "71l6b8ReJKL.jpg"], "Eval": ["713+fQ3rDDL.jpg", "71DjRumR+qL.jpg", "71eR3SiXWXL._SL1600_.jpg", "71EHMc3GcAL.jpg", "B1OZBamnc+S._SL1600_.jpg", "61onWp7u37L.jpg", "71KSUWzc6OL.jpg", "71fg3jp-CEL.jpg", "71NVG4MGqXL.jpg", "71SjU0CldQL.jpg", "71QQ4uZ7TFL.jpg", "71aJgT--wqL.jpg", "615csb-TwQL._SL1600_.jpg"]}, "Negative": ["710fDlnvwML.jpg", "B1DoVbkv9gS._SL1600_.jpg", "811JiT+knOL._SL1600_.jpg", "7158CjMSdNL.jpg", "71262mas-NL.jpg", "71PccM97RjL.jpg", "718BhWiModL.jpg", "61knpArnJSL.jpg", "71TdbwJiY4L._SL1600_.jpg", "81zi0V7xxYL.jpg", "61O9dWDpDyL._SL1600_.jpg", "71DGYBjLwpL.jpg", "81u1pGokDML.jpg", "41jTa38vyQL._SL1600_.jpg", "712pZaHUXRL.jpg", "71BRFqqua8L.jpg", "71aVTP0GH3L._SL1600_.jpg", "71UNoFcbJOL.jpg", "71IdQoqFIDL.jpg", "71HYA1A9w6L.jpg", "B01H1LM9TK-1.jpg", "B01H1LM9TK-2.jpg", "B01H1LM9TK-3.jpg", "B01H1LM9TK-4.jpg"]}, "B01M0MBANV": {"Positive": {"Ref": ["71irtIXqXpL.jpg", "71SZ7fjpnUL.jpg", "61knpArnJSL.jpg"], "Eval": ["71BRFqqua8L.jpg", "713oMngfLdL.jpg", "718BhWiModL.jpg", "617K+XyElYL.jpg"]}, "Negative": ["71KSUWzc6OL.jpg", "71l6b8ReJKL.jpg", "712pZaHUXRL.jpg", "71EHMc3GcAL.jpg", "81u1pGokDML.jpg", "615csb-TwQL._SL1600_.jpg", "71UADUdLSQL.jpg", "713+fQ3rDDL.jpg", "71SjU0CldQL.jpg", "71NVG4MGqXL.jpg", "71DjRumR+qL.jpg", "71WuVqTzCAL.jpg", "B01M0MBANV-0.jpg", "B01M0MBANV-1.jpg", "B01M0MBANV-2.jpg", "B01M0MBANV-3.jpg", "B01M0MBANV-4.jpg"]}, "blisstotes laundry hamper": {"Positive": {"Ref": ["d63223e2.jpeg", "c4c26984.jpeg", "28a80eda.jpeg", "b78c34aa.jpeg"], "Eval": ["356c222e.jpeg", "af3628d1.jpeg", "af68c513.jpeg", "e11ccf6b.jpeg", "49e29208.jpeg", "6804453f.jpeg", "a68da323.jpeg", "804610a5.jpeg", "92cfb53c.jpeg", "14b808eb.jpeg", "49360583.jpeg", "cbba2d9a.jpeg", "732907f8.jpeg", "d336609a.jpeg"]}, "Negative": ["1822ccf9.jpeg", "73a5cbf4.jpeg", "e96fe02b.jpeg", "6c0c1ad3.jpeg", "47142cee.jpeg", "0e854d06.jpeg", "6426178c.jpeg", "8b47a1f0.jpeg", "c6c8ab50.jpeg", "a7dca3d4.jpeg", "5874b05b.jpeg", "bd28799f.jpeg", "ed9a97c3.jpeg", "3ddad460.jpeg", "0c986781.jpeg", "51e13190.jpeg", "64516e3d.jpeg", "58f400e3.jpeg", "81818893.jpeg", "878ef9f3.jpeg", "2039ee82.jpeg", "d62ab354.jpeg", "ba2bd3ce.jpeg", "0efa478f.jpeg", "c4531843.jpeg", "38e9b3d6.jpeg", "a098860d.jpeg", "05b2f805.jpeg", "07e03adc.jpeg", "3f6b4e39.jpeg", "afcf5a23.jpeg", "e95c0e42.jpeg", "8f57071b.jpeg", "4abb5f91.jpeg", "235c8352.jpeg", "496854b6.jpeg", "1d34cb89.jpeg", "6e9da5c5.jpeg", "d714f86c.jpeg", "a176dcbd.jpeg", "2c16e8b5.jpeg", "9a38b83d.jpeg", "6e9ca47e.jpeg", "02520138.jpeg", "3957923b.jpeg", "765b5d2c.jpeg", "a5e429d1.jpeg", "048cb41f.jpeg", "6718192d.jpeg", "c03ed40c.jpeg", "826689a3.jpeg", "5ef68b60.jpeg", "80b44576.jpeg", "27ee2393.jpeg", "b3f3fb9a.jpeg", "1ce4e8f0.jpeg", "b18befcd.jpeg"]}, "B0085J6S0Y": {"Positive": {"Ref": ["61l1y60w6wL.jpg", "819jGmedFSL.jpg", "717D1GL5JVL._SL1600_.jpg"], "Eval": ["819u7EQcoLL._SL1600_.jpg", "71Z1DVMPDhL.jpg", "91hdbm8wbaL._SL1600_.jpg", "711OPDkzahL.jpg", "71kL27pfQJL.jpg", "B16-y5Cib6S._SL1600_.jpg", "61bVJsIEUKL._SL1600_.jpg", "717Nr-Ku4yL._SL1600_.jpg", "71cjDZakDLL.jpg", "817s0wOIHdL._SL1600_.jpg", "71UWst+dOjL.jpg", "71-QF6-USJL.jpg", "71Juf47z1tL.jpg"]}, "Negative": ["81XS29NYe+L.jpg", "71BP9wHcTSL.jpg", "81vQLKwdp4L.jpg", "71oc88P3gnL.jpg", "615csb-TwQL._SL1600_.jpg", "71262mas-NL.jpg", "71KSUWzc6OL.jpg", "81u1pGokDML.jpg", "71UNoFcbJOL.jpg", "61onWp7u37L.jpg", "71aVTP0GH3L._SL1600_.jpg", "71UADUdLSQL.jpg", "71cMcU66OlL.jpg", "71YdK47HJzL.jpg", "71aUsfkh86L._SL1600_.jpg", "81-99C2CVtL.jpg", "71WuVqTzCAL.jpg", "71+Ljc-4HvL.jpg", "71UEwZxwsuL.jpg", "71EHMc3GcAL.jpg", "71Tey8pwvVL.jpg", "71IcjFDQDyL.jpg", "716O6zL2G7L.jpg", "719bwiAcWSL.jpg", "71hZWA29AfL._SL1600_.jpg"]}, "B073P2LH2V": {"Positive": {"Ref": ["81u1pGokDML.jpg", "71UNoFcbJOL.jpg", "81XS29NYe+L.jpg"], "Eval": ["81mwKTUZgbL.jpg", "71FMAOZVZDL.jpg", "81vQLKwdp4L.jpg", "71aVTP0GH3L._SL1600_.jpg", "716D-gfEgUL.jpg"]}, "Negative": ["71l6b8ReJKL.jpg", "71KSUWzc6OL.jpg", "71262mas-NL.jpg", "71kL27pfQJL.jpg", "71A0uP6FbTL.jpg", "71IdQoqFIDL.jpg", "B073P2LH2V-0.jpg", "B073P2LH2V-1.jpg", "B073P2LH2V-2.jpg", "B073P2LH2V-3.jpg"]}, "B0BK23W2LN": {"Positive": {"Ref": ["61pTmMNoBTL._SL1600_.jpg", "61IhzrwQo5L._SL1600_.jpg", "71k4CaLqS+L._SL1600_.jpg", "71B+nmT4YmL._SL1600_.jpg"], "Eval": ["614NRSg70nL._SL1600_.jpg", "715ZyKGfT7L._SL1600_.jpg", "71EaHBghDAL._SL1600_.jpg", "71D233fxlgL._SL1600_.jpg", "71TdbwJiY4L._SL1600_.jpg", "71YsxK8+qlL._SL1600_.jpg", "61wAdKl74EL._SL1600_.jpg"]}, "Negative": ["71MuGv8XakL._SL1600_.jpg", "71a0nDFT21L._SL1600_.jpg", "B1Q-l20KbeS._SL1600_.jpg", "71UhLfqkpgL.jpg", "61QpWzdDzcL._SL1600_.jpg", "81qhIuDO-EL.jpg", "71FEFaXtTKL.jpg", "81q7Y7PBJ6L._SL1600_.jpg", "71MBVtbMNcL.jpg", "B0BK23W2LN-0.jpg", "B0BK23W2LN-1.jpg", "B0BK23W2LN-2.jpg", "B0BK23W2LN-3.jpg", "B0BK23W2LN-4.jpg"]}, "B01E6P8I8U": {"Positive": {"Ref": ["61jutSV5ePL.jpg", "618a20NEHeL._SL1600_.jpg", "616q3uafM3L._SL1600_.jpg"], "Eval": ["61cNmRS-IpL.jpg", "71D0ptAO+aL.jpg", "619OJ8nXurL._SL1600_.jpg", "71m+rtLnSoL.jpg", "71DR67E52mL.jpg", "61iPgyc6seL.jpg", "71jcAMQr4FL.jpg", "71pOylGP1ML.jpg"]}, "Negative": ["7199TmfeVlL._SL1600_.jpg", "71ORISnnwbL.jpg", "71zZuaDbVAL.jpg", "61-lxm6EtwL._SL1600_.jpg", "B1+ZTqPszAS._SL1600_.jpg", "81RhGxtqp4L._SL1600_.jpg", "619gQNS35AL.jpg", "61Kwq8C9+6L.jpg", "719INZIAJrL.jpg", "41uvWtKFSXL._SL1600_.jpg", "91hqCiIeMIL._SL1600_.jpg", "61raKw9nHuL._SL1600_.jpg", "71B8+79wJOL._SL1600_.jpg", "B1KDXoxqPfS._SL1600_.jpg", "71vS2kj7V2L._SL1600_.jpg", "815n9XP25mL._SL1600_.jpg", "716LVXzA64L._SL1600_.jpg", "91nujLLZ-QL._SL1600_.jpg", "B01E6P8I8U-0.jpg", "B01E6P8I8U-1.jpg", "B01E6P8I8U-2.jpg", "B01E6P8I8U-3.jpg", "B01E6P8I8U-4.jpg"]}, "B01H02QMT8": {"Positive": {"Ref": ["715lTMks9FL.jpg", "71KLteKxudL.jpg", "71UADUdLSQL.jpg", "61jbeHyrPKL.jpg", "71A0uP6FbTL.jpg"], "Eval": ["71aUsfkh86L._SL1600_.jpg", "41jTa38vyQL._SL1600_.jpg", "71jUFhXHhxL.jpg", "81WOzR-v+fL._SL1600_.jpg", "61+FnFxROuL.jpg", "71jF-KPdocL.jpg"]}, "Negative": ["71UWst+dOjL.jpg", "71BP9wHcTSL.jpg", "71cjDZakDLL.jpg", "71cMcU66OlL.jpg", "717Nr-Ku4yL._SL1600_.jpg", "71YdK47HJzL.jpg", "71V8pGecqpL.jpg", "71F6j7de6VL._SL1600_.jpg", "71PccM97RjL.jpg", "81vQLKwdp4L.jpg", "61knpArnJSL.jpg", "71262mas-NL.jpg"]}, "B01N48A8S5": {"Positive": {"Ref": ["61U8+fQOcuL._SL1600_.jpg", "71ORISnnwbL.jpg", "71V8pGecqpL.jpg", "41uvWtKFSXL._SL1600_.jpg"], "Eval": ["61raKw9nHuL._SL1600_.jpg", "710Q5lq1YpL.jpg", "7199TmfeVlL._SL1600_.jpg", "B1+ZTqPszAS._SL1600_.jpg", "61Kwq8C9+6L.jpg", "61tU7TTeDZL.jpg", "61-lxm6EtwL._SL1600_.jpg", "71LR6t2txSL.jpg", "71zEsKqH6oL.jpg", "51BneU3WjSL._SL1600_.jpg", "91hqCiIeMIL._SL1600_.jpg"]}, "Negative": ["616q3uafM3L._SL1600_.jpg", "81RhGxtqp4L._SL1600_.jpg", "619gQNS35AL.jpg", "71DR67E52mL.jpg", "71D0ptAO+aL.jpg", "619OJ8nXurL._SL1600_.jpg", "71zZuaDbVAL.jpg", "61-scf8ze6L.jpg", "71jcAMQr4FL.jpg", "618a20NEHeL._SL1600_.jpg", "71B8+79wJOL._SL1600_.jpg", "71vUTp+prmL.jpg", "B1oqohfaGpS._SL1600_.jpg", "81vQLKwdp4L.jpg", "91nujLLZ-QL._SL1600_.jpg", "81VO6VCUfdL._SL1600_.jpg", "61jutSV5ePL.jpg", "8139PmDg8iL.jpg", "719dKjqcXKL._SL1600_.jpg", "815n9XP25mL._SL1600_.jpg", "B1KDXoxqPfS._SL1600_.jpg", "71yyxgXirCL.jpg", "71-zrbGWDzL.jpg", "81sVejyfoxL._SL1600_.jpg", "716LVXzA64L._SL1600_.jpg", "B01N48A8S5-0.jpg", "B01N48A8S5-1.jpg", "B01N48A8S5-2.jpg", "B01N48A8S5-3.jpg", "B01N48A8S5-4.jpg"]}, "B07HMC9S5P": {"Positive": {"Ref": ["61K0-mfbZPL.jpg", "B1PQwF+gvTS._SL1600_.jpg", "61VT-Z9U4qL._SL1600_.jpg", "61h+r4beoFL._SL1600_.jpg"], "Eval": ["8139PmDg8iL.jpg", "31v5kPsBppL._SL1600_.jpg", "71F6j7de6VL._SL1600_.jpg", "71PccM97RjL.jpg", "71KyOjtDTNL.jpg", "811JiT+knOL._SL1600_.jpg", "7101bZjC8UL._SL1600_.jpg", "61A1WNiQHFL._SL1600_.jpg", "61QpWzdDzcL._SL1600_.jpg", "71dqVJWTNgL.jpg", "711iA1nvc8L.jpg", "51+EchsHcML._SL1600_.jpg", "71RZ1mBNzuL.jpg"]}, "Negative": ["71YsxK8+qlL._SL1600_.jpg", "81qhIuDO-EL.jpg", "71lkSq1ofoL.jpg", "71ZnTEdyDyL.jpg", "717ZPl6FQHL.jpg", "61migsYqbaL.jpg", "71gc4Nh55gL.jpg", "A1xTLYCGTPL._SL1600_.jpg", "71HU1MlKHkL.jpg", "61Jw9uTfwGL.jpg", "B1GK4yX8ptS._SL1600_.jpg", "712u65gXdcL.jpg", "71AgR3ZXUML.jpg", "71Cg58JznCL.jpg", "81q7Y7PBJ6L._SL1600_.jpg", "61O9dWDpDyL._SL1600_.jpg", "71MBVtbMNcL.jpg", "61onWp7u37L.jpg", "71KSUWzc6OL.jpg", "71NDMYM5vWL.jpg", "71oJ5-6blfL._SL1600_.jpg", "717UZocn6uL.jpg", "71NPL3MNGEL.jpg", "812ItVPMYmL._SL1600_.jpg", "71V8pGecqpL.jpg"]}, "B004JJKYX6": {"Positive": {"Ref": ["71FEFaXtTKL.jpg", "C1fsgpJNgfS._SL1600_.jpg", "81mHUvs-ByL.jpg"], "Eval": ["514QNbe7zBL._SL1600_.jpg", "71F0pxPvhmL._SL1600_.jpg", "81dR7Lv4HJL._SL1600_.jpg", "71HU1MlKHkL.jpg"]}, "Negative": ["710d-NZa5aL.jpg", "71UhLfqkpgL.jpg", "71UgiIcQJLL.jpg", "71AgR3ZXUML.jpg", "81q7Y7PBJ6L._SL1600_.jpg", "71MBVtbMNcL.jpg", "B004JJKYX6-0.jpg", "B004JJKYX6-1.jpg", "B004JJKYX6-2.jpg", "B004JJKYX6-3.jpg", "B004JJKYX6-4.jpg"]}, "black mesh handy laundry hamper": {"Positive": {"Ref": ["be9b788b.jpeg", "e09c507e.jpeg", "ac789c28.jpeg", "74539f5f.jpeg"], "Eval": ["e9ebad01.jpeg", "9de5435a.jpeg", "c6b770bd.jpeg", "cc824138.jpeg", "938069e6.jpeg", "c9de64f6.jpeg", "45a69ef3.jpeg", "bc71a45e.jpeg", "31cd985d.jpeg", "6457b3b1.jpeg", "52e24369.jpeg", "040090e4.jpeg", "b509c1d8.jpeg", "94212299.jpeg", "c88197dd.jpeg", "570f81b9.jpeg"]}, "Negative": ["5922db2d.jpeg", "54ccdc73.jpeg", "03aa8cc0.jpeg", "b77dd695.jpeg", "1ee813d8.jpeg", "94a0ca8f.jpeg", "8c356c56.jpeg", "5069e07d.jpeg", "9cea0d5a.jpeg", "7102830f.jpeg", "d7465746.jpeg", "f02bed79.jpeg", "0e23738f.jpeg", "8f8ad274.jpeg", "54f981bf.jpeg", "1ebe2234.jpeg", "3bf21ca8.jpeg", "9750a825.jpeg", "7b2af630.jpeg", "6fefe778.jpeg", "44ff4f99.jpeg", "a782d26c.jpeg", "53da52fa.jpeg", "a4a4b938.jpeg", "28c8c165.jpeg", "7d86a855.jpeg", "8f06142e.jpeg", "6aa08bcd.jpeg", "03619a34.jpeg", "e7fe4b8d.jpeg", "2c9e4621.jpeg", "e5941319.jpeg", "e91c4a6e.jpeg", "96ff97f0.jpeg", "c86f7c41.jpeg", "e875d1ad.jpeg", "d7a09b20.jpeg", "d0c6b02d.jpeg", "104c36fd.jpeg", "edd44a0a.jpeg", "727b9232.jpeg", "28f3bc53.jpeg", "02ca919a.jpeg", "9d25c52f.jpeg", "06be0287.jpeg", "b12703f5.jpeg", "225c5232.jpeg", "447b4d30.jpeg", "644a921d.jpeg", "7984abb0.jpeg", "e9863ae3.jpeg", "04a1e42b.jpeg", "bfc6f968.jpeg", "275a8c06.jpeg", "a880f558.jpeg", "c27836d6.jpeg", "696e3307.jpeg", "b545bf86.jpeg", "ba8808b5.jpeg", "be321b15.jpeg", "046b6c50.jpeg", "3b343877.jpeg", "7eb8e99b.jpeg", "1ebcf441.jpeg", "fd9b57b5.jpeg", "46107fc5.jpeg", "68df1794.jpeg", "5cf2eeba.jpeg", "a4038757.jpeg", "9933d149.jpeg", "771f0ca3.jpeg", "6c980c3c.jpeg", "44cdceee.jpeg", "4e48ad7e.jpeg", "56b38129.jpeg", "6618b375.jpeg", "6a12992a.jpeg", "fc915f3b.jpeg", "d4a56d65.jpeg", "7def4b45.jpeg", "b56c1ce9.jpeg", "bb85d59c.jpeg", "d78a803c.jpeg", "f80039b3.jpeg", "f5b1638f.jpeg", "82064cd5.jpeg", "18c6b075.jpeg", "fec461ab.jpeg", "c683fd84.jpeg", "b5d5349b.jpeg", "2984212f.jpeg", "d4c03891.jpeg", "aff56bfa.jpeg", "6eb57d02.jpeg", "a45133b1.jpeg", "adb721a5.jpeg", "1e1fc892.jpeg", "25a98377.jpeg", "a6f05d74.jpeg", "0527be0c.jpeg", "4f8e62d1.jpeg", "cdf46bf1.jpeg", "eca2db0b.jpeg", "720315d6.jpeg", "b1128631.jpeg", "7a867d51.jpeg", "70660dcb.jpeg", "cf353672.jpeg", "e8882956.jpeg", "118c5283.jpeg", "94decf65.jpeg", "fb075065.jpeg", "49e00c18.jpeg", "c6015c65.jpeg", "48525ddf.jpeg", "f799d4a1.jpeg", "4d0cce03.jpeg", "8d0a821a.jpeg", "b1840014.jpeg", "35da3c7e.jpeg", "db9ee33c.jpeg", "93d4cdd8.jpeg", "2a38e20e.jpeg", "a479dcbd.jpeg", "c1665bf1.jpeg", "409f5e30.jpeg", "fb03ef21.jpeg", "648301b0.jpeg", "65831fd5.jpeg", "7d9e6c83.jpeg", "33423b79.jpeg", "238fdcd3.jpeg", "6e9e2a96.jpeg", "0807a37f.jpeg", "e26f4e44.jpeg", "2caa7628.jpeg", "d3f31f8c.jpeg", "0395312e.jpeg", "5dea15c3.jpeg", "057349db.jpeg", "717c5ed1.jpeg", "e49fa9c1.jpeg"]}, "B00FZGXUSS": {"Positive": {"Ref": ["71WuVqTzCAL.jpg", "71Tey8pwvVL.jpg", "71UEwZxwsuL.jpg"], "Eval": ["712pZaHUXRL.jpg", "712GCZWoyxL.jpg", "71cMcU66OlL.jpg", "71262mas-NL.jpg", "71+Ljc-4HvL.jpg", "71oc88P3gnL.jpg"]}, "Negative": ["716D-gfEgUL.jpg", "71YdK47HJzL.jpg", "91hdbm8wbaL._SL1600_.jpg", "71l6b8ReJKL.jpg", "61onWp7u37L.jpg", "71UNoFcbJOL.jpg", "61knpArnJSL.jpg", "71KSUWzc6OL.jpg", "81u1pGokDML.jpg", "71aVTP0GH3L._SL1600_.jpg", "615csb-TwQL._SL1600_.jpg", "71EHMc3GcAL.jpg", "71UADUdLSQL.jpg", "71UWst+dOjL.jpg", "713+fQ3rDDL.jpg", "B00FZGXUSS-0.jpg", "B00FZGXUSS-1.jpg", "B00FZGXUSS-2.jpg", "B00FZGXUSS-3.jpg", "B00FZGXUSS-4.jpg"]}, "homehacks laundry hamper": {"Positive": {"Ref": ["44c916bc.jpeg", "3bac6484.jpeg", "e13970da.jpeg"], "Eval": ["cbed7565.jpeg", "1188960f.jpeg", "2d445a11.jpeg", "cea11395.jpeg", "4c366b73.jpeg", "8cd68aa5.jpeg", "481be1c6.jpeg", "a9641db4.jpeg", "a9f71ff2.jpeg", "5543c28e.jpeg", "740d93f7.jpeg", "8f91e614.jpeg", "8c109c09.jpeg"]}, "Negative": ["ffca4574.jpeg", "8a7f54e6.jpeg", "d9bf633d.jpeg", "e5df541f.jpeg", "46b8eb18.jpeg", "6087af4d.jpeg", "40093925.jpeg", "ff6c453b.jpeg", "937b2e6a.jpeg", "6ecab7ac.jpeg", "40fd62b9.jpeg", "03b6115e.jpeg", "989e6bf1.jpeg", "8667d0e2.jpeg", "937d58c2.jpeg", "a072d7b2.jpeg", "10e8e54e.jpeg", "c411fe12.jpeg", "34041353.jpeg", "a071ccfc.jpeg", "be1e7c65.jpeg", "c30a648f.jpeg", "b9f6524b.jpeg", "349c4e4b.jpeg", "fcb08b50.jpeg", "fd1afa13.jpeg", "822d36da.jpeg", "239a9e14.jpeg", "3d487d66.jpeg", "9832e793.jpeg", "10ee2a50.jpeg", "55cae067.jpeg", "940dfbaa.jpeg", "4545a507.jpeg", "2a1a1363.jpeg", "622cc061.jpeg", "82bb31b5.jpeg", "22fd75a2.jpeg", "6c5105b8.jpeg", "9934a5da.jpeg", "3af51c4f.jpeg", "e1f4cbf6.jpeg", "cf76b44b.jpeg", "7fc9017b.jpeg", "74ecbca5.jpeg", "ced4bd23.jpeg", "35d617fb.jpeg", "9680d9d9.jpeg", "5b3636c2.jpeg", "a0fa7099.jpeg", "444e218b.jpeg", "84dd3b6e.jpeg", "4a48030e.jpeg", "f78711ac.jpeg", "87449aaf.jpeg", "c9c1c327.jpeg", "19fc6a52.jpeg", "a5f96c6c.jpeg", "8a650118.jpeg", "938389f9.jpeg", "24346c70.jpeg", "9c9cde3f.jpeg", "0fd18a75.jpeg", "92f2cfd8.jpeg", "00476a23.jpeg", "2203e57f.jpeg", "c373dbcf.jpeg", "35894466.jpeg", "affb8477.jpeg", "0cf053a4.jpeg", "0650f6fb.jpeg", "0f3cd456.jpeg", "0e3bac9b.jpeg", "e174f72c.jpeg", "95ffa279.jpeg", "6ae1665c.jpeg", "b78de157.jpeg", "73e24b55.jpeg", "90988bad.jpeg", "ce19345d.jpeg", "80bd34bc.jpeg", "1bd62c8a.jpeg", "d15fa9fd.jpeg", "ea6710cc.jpeg", "d830587f.jpeg", "0faa7905.jpeg", "72180e74.jpeg", "3ed9a188.jpeg", "7b589592.jpeg", "628a2d72.jpeg", "827522fe.jpeg", "741f8ce8.jpeg", "93f1a5dd.jpeg", "43a0006b.jpeg", "136fb21c.jpeg", "de048051.jpeg", "04623171.jpeg", "2293aecf.jpeg", "50e6353f.jpeg", "0d365537.jpeg", "052de3e5.jpeg", "199c10a8.jpeg", "a077601c.jpeg", "bf44f6a2.jpeg", "cf1029cf.jpeg", "333fb566.jpeg", "fbc36f2d.jpeg", "b7f08ef0.jpeg", "6a6446fa.jpeg", "a34119ed.jpeg", "b04a9278.jpeg", "20fab5c2.jpeg", "21c3019a.jpeg", "e2c4a066.jpeg", "9bf6d10b.jpeg", "8f0ee3f2.jpeg", "125f673d.jpeg", "78cc6c76.jpeg", "27588bfd.jpeg", "84244113.jpeg", "85923aed.jpeg", "5fae0d07.jpeg", "f018fe50.jpeg", "a8a86c0d.jpeg", "07d49648.jpeg", "2db558ea.jpeg", "ada41e14.jpeg", "75997d33.jpeg", "c0524d51.jpeg", "8054b65f.jpeg", "bc74d8ea.jpeg", "2405bac0.jpeg", "f066c1f8.jpeg", "3565af65.jpeg", "ebd058cb.jpeg", "1491ac06.jpeg", "41a71edc.jpeg", "e6bcd3f2.jpeg", "abb9d180.jpeg", "3347e7e8.jpeg", "f62c605c.jpeg", "e0fc5982.jpeg"]}, "B06Y19N3BK": {"Positive": {"Ref": ["71NPL3MNGEL.jpg", "71-Ea4hc6QL.jpg", "71HuPhN3mOL.jpg"], "Eval": ["81DBH2l5-dL._SL1600_.jpg", "C1odGsj3XaS._SL1600_.jpg", "61QJEYLulEL.jpg", "B1Q-l20KbeS._SL1600_.jpg", "81THVjfCKrL._SL1600_.jpg"]}, "Negative": ["71dqVJWTNgL.jpg", "61Jw9uTfwGL.jpg", "61UuCfk634L.jpg", "71F9TQDZGCL._SL1600_.jpg", "71y7v2QpCwL.jpg", "61K0-mfbZPL.jpg", "61A1WNiQHFL._SL1600_.jpg", "71HU1MlKHkL.jpg", "B06Y19N3BK-0.jpg", "B06Y19N3BK-1.jpg", "B06Y19N3BK-2.jpg", "B06Y19N3BK-3.jpg", "B06Y19N3BK-4.jpg"]}}